postreise/__init__.py
postreise/analyze/__init__.py
postreise/analyze/demand.py
postreise/analyze/time.py
postreise/analyze/generation/__init__.py
postreise/analyze/generation/binding.py
postreise/analyze/generation/capacity.py
postreise/analyze/generation/costs.py
postreise/analyze/generation/curtailment.py
postreise/analyze/generation/emissions.py
postreise/analyze/generation/summarize.py
postreise/analyze/generation/tests/__init__.py
postreise/analyze/generation/tests/test_binding.py
postreise/analyze/generation/tests/test_capacity.py
postreise/analyze/generation/tests/test_costs.py
postreise/analyze/generation/tests/test_curtailment.py
postreise/analyze/generation/tests/test_emissions.py
postreise/analyze/generation/tests/test_summarize.py
postreise/analyze/tests/__init__.py
postreise/analyze/tests/test_demand.py
postreise/analyze/tests/test_time.py
postreise/analyze/transmission/__init__.py
postreise/analyze/transmission/congestion.py
postreise/analyze/transmission/utilization.py
postreise/analyze/transmission/tests/__init__.py
postreise/analyze/transmission/tests/test_congestion_surplus.py
postreise/analyze/transmission/tests/test_utilization.py
postreise/data/2016_Historical_Texas_Capacity_GW.csv
postreise/data/2016_Historical_Texas_Generation_TWh.csv
postreise/data/2016_Historical_USA_TAMU_Capacity_MW.csv
postreise/data/2016_Historical_USA_TAMU_Generation_GWh.csv
postreise/data/2016_Historical_Western_Capacity_GW.csv
postreise/data/2016_Historical_Western_Generation_TWh.csv
postreise/data/2016_NREL_Low_Demand_Western_Generation_TWh.csv
postreise/data/2016_NREL_Mid_Case_Western_Generation_TWh.csv
postreise/data/2030_USA_Clean_Energy_Ambitious_Targets.csv
postreise/data/2030_USA_Clean_Energy_Regular_Targets.csv
postreise/data/__init__.py
postreise/plot/__init__.py
postreise/plot/canvas.py
postreise/plot/check.py
postreise/plot/colors.py
postreise/plot/plot_bar_generation_max_min_actual.py
postreise/plot/plot_bar_generation_stack.py
postreise-0.5.3.dist-info/LICENSE
postreise-0.5.3.dist-info/METADATA
postreise-0.5.3.dist-info/WHEEL
postreise-0.5.3.dist-info/top_level.txt
postreise-0.5.3.dist-info/RECORD
