Metadata-Version: 2.1
Name: postreise
Version: 0.5.3
Summary: Extract, analyze and plot data from scenario
Home-page: https://github.com/Breakthrough-Energy/PostREISE
Author: Breakthrough Energy
Author-email: sciences@breakthroughenergy.org
Project-URL: Bug Tracker, https://github.com/Breakthrough-Energy/PostREISE/issues
Classifier: License :: OSI Approved :: MIT License
Classifier: Operating System :: OS Independent
Classifier: Programming Language :: Python :: 3.7
Classifier: Programming Language :: Python :: 3.8
Classifier: Programming Language :: Python :: 3.9
Classifier: Programming Language :: Python :: 3.10
Requires-Python: >=3.8
License-File: LICENSE
Requires-Dist: powersimdata (~=0.5.5)
Requires-Dist: bokeh
Requires-Dist: matplotlib
Requires-Dist: pyproj
